.DS_Store
hydraflask/.DS_Store
hydraflask/__init__.py
hydraflask/__main__.py
hydraflask/hydra.py
hydraflask/templates/__init__.py
hydraflask/templates/base_template.txt
hydraflask/templates/config_template.txt
hydraflask/templates/form_template.txt
hydraflask/templates/requirements_template.txt
hydraflask/templates/theme_template.txt
hydraflask-0.3.1.dist-info/LICENSE
hydraflask-0.3.1.dist-info/METADATA
hydraflask-0.3.1.dist-info/WHEEL
hydraflask-0.3.1.dist-info/top_level.txt
hydraflask-0.3.1.dist-info/RECORD
