Metadata-Version: 2.1
Name: hydraflask
Version: 0.3.1
Summary: Automator for web frameworks
Home-page: https://github.com/chaiyawahoo/HydraFlask/
Author: Chaiyawat Nunes
Author-email: chaiyawahoo@gmail.com
License: UNKNOWN
Project-URL: Bug Tracker, https://github.com/chaiyawahoo/HydraFlask/issues
Platform: UNKNOWN
Classifier: Development Status :: 3 - Alpha
Classifier: Natural Language :: English
Classifier: Programming Language :: Python :: 3
Classifier: Topic :: Software Development :: Code Generators
Classifier: License :: OSI Approved :: MIT License
Classifier: Operating System :: OS Independent
Requires-Python: >=3.6
Requires-Dist: autopep8 (==1.5.5)
Requires-Dist: pycodestyle (==2.6.0)
Requires-Dist: toml (==0.10.2)
